Workbook

Sheet Смета
A1: Смета по проекту: Ответ на уведомление экспертизы
A2: Исполнитель: Демо-фирма «Слайд 3»
A3: Заказчик: ИП Смирнов
A4: Дата: 25.10.2026
A5: Налоговый режим: УСН «доходы» 6% + НДС 5%
A7: № | B7: Этап | C7: Исполнитель | D7: Часы | E7: Ставка, ₽/ч | F7: Стоимость, ₽
A8: 1 | B8: Анализ уведомления и ответ | C8: Партнёр (Партнёр) | D8: 2 | E8: 10000 | F8: =D8*E8
A9: 2 | B9: Анализ уведомления и ответ | C9: Юрист (Младший юрист) | D9: 10 | E9: 5000 | F9: =D9*E9
B10: Стоимость по ставкам | F10: =SUM(F8:F9)
B11: Скидка до потолка стоимости | F11: =MIN(F10,60000)-F10
B12: Итого за услуги без НДС | F12: =F10+F11
B13: НДС 5% | F13: =F12*0.05
B15: Итого к оплате | F15: =F12+F13
A18: Смета действительна 14 дней с даты составления.

Sheet Внутренний расчёт
A1: Внутренний расчёт проекта
A3: Показатель | B3: Значение
A4: Выручка за услуги без НДС, ₽ | B4: =MIN(SUM('Исходные данные'!$J$35:$J$36),'Исходные данные'!$B$8)/(1+'Исходные данные'!$B$15*'Исходные данные'!$B$7)
A5: НДС (сверху), ₽ | B5: ='Исходные данные'!$B$15*$B$4
A6: Возмещаемые расходы, ₽ | B6: =SUMIF('Исходные данные'!$B$40:$B$40,"возмещаемый",'Исходные данные'!$G$40:$G$40)
A7: Итого к оплате клиентом, ₽ | B7: =$B$4+$B$5+$B$6
A8: Прямые трудозатраты, ₽ | B8: =SUM('Исходные данные'!$K$35:$K$36)
A9: в т. ч. стоимость недозагрузки, ₽ | B9: =SUM('Исходные данные'!$L$35:$L$36)
A10: Накладные (распределённые), ₽ | B10: ='Исходные данные'!$B$31*SUM('Исходные данные'!$D$35:$D$36)
A11: Собственные расходы, ₽ | B11: =SUMIF('Исходные данные'!$B$40:$B$40,"собственный",'Исходные данные'!$G$40:$G$40)
A12: Все издержки проекта, ₽ | B12: =$B$8+$B$10+$B$11
A13: Налог на доход или прибыль, ₽ | B13: =MAX($B$33,$B$34)
A14: Чистая прибыль (NNE), ₽ | B14: =$B$4-$B$12-$B$13
A15: Маржа, % | B15: =IF($B$4>0,$B$14/$B$4,0)
A16: Целевая маржа, % | B16: ='Исходные данные'!$B$9
A17: Ставка накладных, ₽/ч | B17: ='Исходные данные'!$B$31
A18: Средневзвешенная ставка, ₽/ч | B18: =IF(SUM('Исходные данные'!$D$35:$D$36)>0,SUM('Исходные данные'!$J$35:$J$36)/SUM('Исходные данные'!$D$35:$D$36),0)
A19: Коэффициент рычага | B19: =IF(SUMIF('Исходные данные'!$C$35:$C$36,"старший",'Исходные данные'!$D$35:$D$36)>0,SUMIF('Исходные данные'!$C$35:$C$36,"младший",'Исходные данные'!$D$35:$D$36)/SUMIF('Исходные данные'!$C$35:$C$36,"старший",'Исходные данные'!$D$35:$D$36),0)
A20: Налоговый режим | B20: УСН «доходы» 6% + НДС 5%
A23: Анализ этапов
A24: Этап | B24: Часы | C24: Выручка этапа, ₽ | D24: Издержки этапа, ₽ | E24: Налог этапа, ₽ | F24: NNE этапа, ₽ | G24: Маржа, % | H24: Статус | I24: Теневая стоимость, ₽ | J24: Трудозатраты, ₽ | K24: Взносы на часах, ₽ | L24: Из прибыли, ₽ | M24: Свои расходы этапа, ₽ | N24: Доля выручки
A25: Анализ уведомления и ответ | B25: =SUMIF('Исходные данные'!$A$35:$A$36,$A25,'Исходные данные'!$D$35:$D$36) | C25: =$B$4*N25 | D25: =J25+'Исходные данные'!$B$31*B25+M25+($B$11-SUM($M$25:$M$25))*N25 | E25: =IF($B$35="по ставке с выручки этапа",'Исходные данные'!$B$12*C25-IF('Исходные данные'!$B$14>0,K25,0),IF($B$35="по прибыли этапа",'Исходные данные'!$B$12*(C25-D25+L25),IF($B$4>0,$B$13*C25/$B$4,0))) | F25: =C25-D25-E25 | G25: =IF(C25>0,F25/C25,0) | H25: =IF(ROUND(G25,6)<=0,"Убыточный",IF(ROUND(G25,6)>=$B$16,"Норма","Низкая маржа")) | I25: =SUMIF('Исходные данные'!$A$35:$A$36,$A25,'Исходные данные'!$J$35:$J$36) | J25: =SUMIF('Исходные данные'!$A$35:$A$36,$A25,'Исходные данные'!$K$35:$K$36) | K25: =SUMIF('Исходные данные'!$A$35:$A$36,$A25,'Исходные данные'!$M$35:$M$36) | L25: =SUMIF('Исходные данные'!$A$35:$A$36,$A25,'Исходные данные'!$N$35:$N$36) | M25: =SUMIFS('Исходные данные'!$G$40:$G$40,'Исходные данные'!$B$40:$B$40,"собственный",'Исходные данные'!$C$40:$C$40,$A25) | N25: =IF(SUM('Исходные данные'!$J$35:$J$36)>0,I25/SUM('Исходные данные'!$J$35:$J$36),IF(SUM('Исходные данные'!$K$35:$K$36)>0,J25/SUM('Исходные данные'!$K$35:$K$36),IF(SUM('Исходные данные'!$D$35:$D$36)>0,B25/SUM('Исходные данные'!$D$35:$D$36),0)))
A27: Расчёт налога
A28: База налога | B28: ='Исходные данные'!$B$11
A29: Взносы на часах проекта S | B29: =SUM('Исходные данные'!$M$35:$M$36)
A30: Вознаграждение из прибыли N | B30: =SUM('Исходные данные'!$N$35:$N$36)
A31: Налоговая база | B31: =IF($B$28="доходы",$B$4,MAX($B$4-$B$12+$B$30,0))
A32: Уменьшение налога на взносы | B32: =IF($B$28="доходы",MIN($B$29,'Исходные данные'!$B$14*'Исходные данные'!$B$12*$B$4),0)
A33: Налог до минимального | B33: ='Исходные данные'!$B$12*$B$31-$B$32
A34: Минимальный налог | B34: ='Исходные данные'!$B$13*$B$4
A35: Налог этапов | B35: =IF(AND($B$28="доходы",IF('Исходные данные'!$B$14>0,$B$29,0)<=$B$32),"по ставке с выручки этапа",IF(AND(NOT($B$28="доходы"),$B$34<=$B$33,$B$13>0),"по прибыли этапа","пропорционально выручке"))

Sheet Исходные данные
A1: Исходные данные расчёта
A2: Суммы — в валюте проекта после пересчёта по курсам. Синие ячейки — входные данные, чёрные — формулы; листы «Смета» и «Внутренний расчёт» пересчитываются по ним.
A4: Параметры
A5: Валюта проекта | B5: RUB
A6: Модель цены | B6: почасовая с потолком
A7: Цены указаны с НДС (1 — да, 0 — нет) | B7: 0
A8: Потолок или согласованная цена | B8: 60000
A9: Целевая маржа m* | B9: 0.3
A10: Налоговый режим | B10: УСН «доходы» 6% + НДС 5%
A11: База налога | B11: доходы
A12: Ставка налога t | B12: 0.06
A13: Минимальный налог t_min | B13: 0
A14: Предел уменьшения налога на взносы κ | B14: 0.5
A15: Ставка НДС v | B15: 0.05
A17: Команда фирмы
A18: Сотрудник | B18: Роль | C18: Группа для рычага | D18: Валюта | E18: Курс к валюте проекта | F18: Оклад или сумма в месяц | G18: Ставка взносов | H18: Взносы в стране расчёта (1/0) | I18: Контрактные часы H | J18: Утилизация u | K18: Ставка для клиента | L18: Из прибыли (1/0) | M18: W = оклад × (1 + взносы) | N18: K = H × u | O18: c = W × курс / K | P18: ĉ = W × курс / H | Q18: s = взносы × курс / K | R18: b = ставка × курс
A19: Партнёр | B19: Партнёр | C19: старший | D19: RUB | E19: 1 | F19: 400000 | G19: 0 | H19: 1 | I19: 160 | J19: 0.625 | K19: 10000 | L19: 0 | M19: =F19*(1+G19) | N19: =I19*J19 | O19: =M19*E19/N19 | P19: =M19*E19/I19 | Q19: =H19*F19*G19*E19/N19 | R19: =K19*E19
A20: Юрист | B20: Младший юрист | C20: младший | D20: RUB | E20: 1 | F20: 150000 | G20: 0 | H20: 1 | I20: 160 | J20: 0.625 | K20: 5000 | L20: 0 | M20: =F20*(1+G20) | N20: =I20*J20 | O20: =M20*E20/N20 | P20: =M20*E20/I20 | Q20: =H20*F20*G20*E20/N20 | R20: =K20*E20
A21: Стажёр | B21: Стажёр | C21: младший | D21: RUB | E21: 1 | F21: 50000 | G21: 0 | H21: 1 | I21: 160 | J21: 0.625 | K21: 2000 | L21: 0 | M21: =F21*(1+G21) | N21: =I21*J21 | O21: =M21*E21/N21 | P21: =M21*E21/I21 | Q21: =H21*F21*G21*E21/N21 | R21: =K21*E21
A23: Накладные фирмы
A24: Накладной расход | B24: Сумма | C24: Валюта | D24: Курс к валюте проекта | E24: Период | F24: Доля в месяц | G24: В месяц = сумма × курс × доля
A25: Аренда офиса | B25: 18000 | C25: RUB | D25: 1 | E25: в месяц | F25: 1 | G25: =B25*D25*F25
A26: Правовые базы и ПО | B26: 7000 | C26: RUB | D26: 1 | E26: в месяц | F26: 1 | G26: =B26*D26*F26
A27: Бухгалтерия на аутсорсе | B27: 5000 | C27: RUB | D27: 1 | E27: в месяц | F27: 1 | G27: =B27*D27*F27
A29: Накладные в месяц | B29: =SUM($G$25:$G$27)
A30: Биллируемая ёмкость фирмы, ч/мес | B30: =SUM($N$19:$N$21)
A31: Ставка накладных ρ = накладные / ёмкость | B31: =IF($B$30>0,$B$29/$B$30,0)
A33: Назначения
A34: Этап | B34: Сотрудник | C34: Группа для рычага | D34: Часы h | E34: Ставка b | F34: Себестоимость часа c | G34: Контрактного часа ĉ | H34: Взносы на час s | I34: Из прибыли | J34: V = b × h | K34: Трудозатраты c × h | L34: Недозагрузка (c − ĉ) × h | M34: Взносы s × h | N34: Из прибыли c × h
A35: Анализ уведомления и ответ | B35: Партнёр | C35: =C19 | D35: 2 | E35: =R19 | F35: =O19 | G35: =P19 | H35: =Q19 | I35: =L19 | J35: =E35*D35 | K35: =F35*D35 | L35: =(F35-G35)*D35 | M35: =H35*D35 | N35: =IF(I35=1,K35,0)
A36: Анализ уведомления и ответ | B36: Юрист | C36: =C20 | D36: 10 | E36: =R20 | F36: =O20 | G36: =P20 | H36: =Q20 | I36: =L20 | J36: =E36*D36 | K36: =F36*D36 | L36: =(F36-G36)*D36 | M36: =H36*D36 | N36: =IF(I36=1,K36,0)
A38: Расходы проекта
A39: Расход | B39: Тип | C39: Этап | D39: Сумма | E39: Валюта | F39: Курс к валюте проекта | G39: В валюте проекта
